pytest_delta/__init__.py
pytest_delta/config.py
pytest_delta/delta.py
pytest_delta/git.py
pytest_delta/graph.py
pytest_delta/plugin.py
pytest_delta-1.0.0.dist-info/METADATA
pytest_delta-1.0.0.dist-info/WHEEL
pytest_delta-1.0.0.dist-info/entry_points.txt
pytest_delta-1.0.0.dist-info/licenses/LICENSE
pytest_delta-1.0.0.dist-info/RECORD
