Metadata-Version: 2.4
Name: pytest-delta
Version: 1.0.0
Summary: Run only tests impacted by your code changes (delta-based selection) for pytest.
License: MIT
License-File: LICENSE
Keywords: pytest,plugin,selective,impact,test,ci,graph,performance,incremental
Author: Cem Alptürk
Author-email: cem.alpturk@gmail.com
Requires-Python: >=3.12
Classifier: Development Status :: 4 - Beta
Classifier: Framework :: Pytest
Classifier: Intended Audience :: Developers
Classifier: License :: OSI Approved :: MIT License
Classifier: Programming Language :: Python :: 3
Classifier: Programming Language :: Python :: 3.12
Classifier: Programming Language :: Python :: 3.13
Classifier: Programming Language :: Python :: 3.14
Classifier: Topic :: Software Development :: Testing
Requires-Dist: msgpack (>=1.0.0,<2.0.0)
Requires-Dist: pytest (>=9.0.2,<10.0.0)
Project-URL: Homepage, https://github.com/CemAlpturk/pytest-delta
Project-URL: Repository, https://github.com/CemAlpturk/pytest-delta
